[{"id":0,"previousHash":"0","timestamp":1514851200000,"transactions":[],"nonce":0,"hash":"e3b0c44298fc1c149afbf4c8996fb92427ae41e4649b934ca495991b7852b855"},{"id":1,"previousHash":"e3b0c44298fc1c149afbf4c8996fb92427ae41e4649b934ca495991b7852b855","timestamp":1548715686375,"transactions":[{"fromAddr":null,"toAddr":"0418b84ba62e0447949ca6837b697842aba1bca946968b81c4b77abe7adfa0b8b4e5058d943f697963b1027c71ebe8feb50c309cee70e1c3692c0ce9ee458dcdae","pokemon":["{\"id\":\"mGRko05MOdvCzDSeGU8xO\",\"Pokemon\":{\"id\":510,\"name\":{\"english\":\"Liepard\",\"japanese\":\"レパルダス\",\"chinese\":\"酷豹\"},\"type\":[\"Dark\"],\"base\":{\"HP\":64,\"Attack\":88,\"Defense\":50,\"Sp. Attack\":88,\"Sp. Defense\":50,\"Speed\":106}},\"Shiny\":false,\"IVs\":{\"hp\":27,\"attack\":28,\"defense\":2,\"speed\":25,\"spatk\":28,\"spdef\":12},\"OriginalOwner\":\"0418b84ba62e0447949ca6837b697842aba1bca946968b81c4b77abe7adfa0b8b4e5058d943f697963b1027c71ebe8feb50c309cee70e1c3692c0ce9ee458dcdae\",\"Gender\":\"male\"}","{\"id\":\"Qpd_zMv3ZKY0yMOYO77cq\",\"Pokemon\":{\"id\":220,\"name\":{\"english\":\"Swinub\",\"japanese\":\"ウリムー\",\"chinese\":\"小山猪\"},\"type\":[\"Ice\",\"Ground\"],\"base\":{\"HP\":50,\"Attack\":50,\"Defense\":40,\"Sp. Attack\":30,\"Sp. Defense\":30,\"Speed\":50}},\"Shiny\":false,\"IVs\":{\"hp\":26,\"attack\":12,\"defense\":14,\"speed\":16,\"spatk\":25,\"spdef\":23},\"OriginalOwner\":\"0418b84ba62e0447949ca6837b697842aba1bca946968b81c4b77abe7adfa0b8b4e5058d943f697963b1027c71ebe8feb50c309cee70e1c3692c0ce9ee458dcdae\",\"Gender\":\"male\"}","{\"id\":\"8svKhe25HT9cn8B_utcTh\",\"Pokemon\":{\"id\":375,\"name\":{\"english\":\"Metang\",\"japanese\":\"メタング\",\"chinese\":\"金属怪\"},\"type\":[\"Steel\",\"Psychic\"],\"base\":{\"HP\":60,\"Attack\":75,\"Defense\":100,\"Sp. Attack\":55,\"Sp. Defense\":80,\"Speed\":50}},\"Shiny\":false,\"IVs\":{\"hp\":15,\"attack\":30,\"defense\":0,\"speed\":1,\"spatk\":18,\"spdef\":16},\"OriginalOwner\":\"0418b84ba62e0447949ca6837b697842aba1bca946968b81c4b77abe7adfa0b8b4e5058d943f697963b1027c71ebe8feb50c309cee70e1c3692c0ce9ee458dcdae\",\"Gender\":\"male\"}","{\"id\":\"w3SIZ7UYgl5_UTcHE46WY\",\"Pokemon\":{\"id\":277,\"name\":{\"english\":\"Swellow\",\"japanese\":\"オオスバメ\",\"chinese\":\"大王燕\"},\"type\":[\"Normal\",\"Flying\"],\"base\":{\"HP\":60,\"Attack\":85,\"Defense\":60,\"Sp. Attack\":75,\"Sp. Defense\":50,\"Speed\":125}},\"Shiny\":false,\"IVs\":{\"hp\":1,\"attack\":15,\"defense\":18,\"speed\":28,\"spatk\":19,\"spdef\":30},\"OriginalOwner\":\"0418b84ba62e0447949ca6837b697842aba1bca946968b81c4b77abe7adfa0b8b4e5058d943f697963b1027c71ebe8feb50c309cee70e1c3692c0ce9ee458dcdae\",\"Gender\":\"male\"}","{\"id\":\"iMMBV632NPV2GwKN4wGAN\",\"Pokemon\":{\"id\":306,\"name\":{\"english\":\"Aggron\",\"japanese\":\"ボスゴドラ\",\"chinese\":\"波士可多拉\"},\"type\":[\"Steel\",\"Rock\"],\"base\":{\"HP\":70,\"Attack\":110,\"Defense\":180,\"Sp. Attack\":60,\"Sp. Defense\":60,\"Speed\":50}},\"Shiny\":false,\"IVs\":{\"hp\":14,\"attack\":14,\"defense\":4,\"speed\":12,\"spatk\":10,\"spdef\":7},\"OriginalOwner\":\"0418b84ba62e0447949ca6837b697842aba1bca946968b81c4b77abe7adfa0b8b4e5058d943f697963b1027c71ebe8feb50c309cee70e1c3692c0ce9ee458dcdae\",\"Gender\":\"male\"}","{\"id\":\"kY6EJDaeLf2hMU9FCBz-q\",\"Pokemon\":{\"id\":771,\"name\":{\"english\":\"Pyukumuku\",\"japanese\":\"ナマコブシ\",\"chinese\":\"拳海参\"},\"type\":[\"Water\"],\"base\":{\"HP\":55,\"Attack\":60,\"Defense\":130,\"Sp. Attack\":30,\"Sp. Defense\":130,\"Speed\":5}},\"Shiny\":false,\"IVs\":{\"hp\":7,\"attack\":6,\"defense\":11,\"speed\":3,\"spatk\":17,\"spdef\":18},\"OriginalOwner\":\"0418b84ba62e0447949ca6837b697842aba1bca946968b81c4b77abe7adfa0b8b4e5058d943f697963b1027c71ebe8feb50c309cee70e1c3692c0ce9ee458dcdae\",\"Gender\":\"male\"}"],"timeStamp":1548715686375}],"nonce":104,"hash":"00e92ab80352a385354f31627dd16412384e40c6bb4747b2614921a6d20ae89c"},{"id":2,"previousHash":"00e92ab80352a385354f31627dd16412384e40c6bb4747b2614921a6d20ae89c","timestamp":1548715710409,"transactions":[{"fromAddr":null,"toAddr":"0418b84ba62e0447949ca6837b697842aba1bca946968b81c4b77abe7adfa0b8b4e5058d943f697963b1027c71ebe8feb50c309cee70e1c3692c0ce9ee458dcdae","pokemon":["{\"id\":\"Hz0aPMNazlUhqayytJrPg\",\"Pokemon\":{\"id\":571,\"name\":{\"english\":\"Zoroark\",\"japanese\":\"ゾロアーク\",\"chinese\":\"索罗亚克\"},\"type\":[\"Dark\"],\"base\":{\"HP\":60,\"Attack\":105,\"Defense\":60,\"Sp. Attack\":120,\"Sp. Defense\":60,\"Speed\":105}},\"Shiny\":false,\"IVs\":{\"hp\":18,\"attack\":18,\"defense\":15,\"speed\":21,\"spatk\":9,\"spdef\":7},\"OriginalOwner\":\"0418b84ba62e0447949ca6837b697842aba1bca946968b81c4b77abe7adfa0b8b4e5058d943f697963b1027c71ebe8feb50c309cee70e1c3692c0ce9ee458dcdae\",\"Gender\":\"male\"}","{\"id\":\"_xEw3LyNk8NKgRrdFFFxN\",\"Pokemon\":{\"id\":800,\"name\":{\"english\":\"Necrozma\",\"japanese\":\"ネクロズマ\",\"chinese\":\"奈克洛兹玛\"},\"type\":[\"Psychic\"],\"base\":{\"HP\":97,\"Attack\":107,\"Defense\":101,\"Sp. Attack\":127,\"Sp. Defense\":89,\"Speed\":79}},\"Shiny\":false,\"IVs\":{\"hp\":17,\"attack\":4,\"defense\":17,\"speed\":15,\"spatk\":27,\"spdef\":29},\"OriginalOwner\":\"0418b84ba62e0447949ca6837b697842aba1bca946968b81c4b77abe7adfa0b8b4e5058d943f697963b1027c71ebe8feb50c309cee70e1c3692c0ce9ee458dcdae\",\"Gender\":\"male\"}","{\"id\":\"T4R9Y3jjfuywgwrICMzP4\",\"Pokemon\":{\"id\":411,\"name\":{\"english\":\"Bastiodon\",\"japanese\":\"トリデプス\",\"chinese\":\"护城龙\"},\"type\":[\"Rock\",\"Steel\"],\"base\":{\"HP\":60,\"Attack\":52,\"Defense\":168,\"Sp. Attack\":47,\"Sp. Defense\":138,\"Speed\":30}},\"Shiny\":false,\"IVs\":{\"hp\":23,\"attack\":0,\"defense\":2,\"speed\":0,\"spatk\":21,\"spdef\":4},\"OriginalOwner\":\"0418b84ba62e0447949ca6837b697842aba1bca946968b81c4b77abe7adfa0b8b4e5058d943f697963b1027c71ebe8feb50c309cee70e1c3692c0ce9ee458dcdae\",\"Gender\":\"male\"}","{\"id\":\"hg4ACWgEnLMgLYVNtytZE\",\"Pokemon\":{\"id\":546,\"name\":{\"english\":\"Cottonee\",\"japanese\":\"モンメン\",\"chinese\":\"木棉球\"},\"type\":[\"Grass\",\"Fairy\"],\"base\":{\"HP\":40,\"Attack\":27,\"Defense\":60,\"Sp. Attack\":37,\"Sp. Defense\":50,\"Speed\":66}},\"Shiny\":false,\"IVs\":{\"hp\":17,\"attack\":14,\"defense\":2,\"speed\":26,\"spatk\":4,\"spdef\":9},\"OriginalOwner\":\"0418b84ba62e0447949ca6837b697842aba1bca946968b81c4b77abe7adfa0b8b4e5058d943f697963b1027c71ebe8feb50c309cee70e1c3692c0ce9ee458dcdae\",\"Gender\":\"male\"}","{\"id\":\"_SuXzK6PFTukYjxHtS0hO\",\"Pokemon\":{\"id\":322,\"name\":{\"english\":\"Numel\",\"japanese\":\"ドンメル\",\"chinese\":\"呆火驼\"},\"type\":[\"Fire\",\"Ground\"],\"base\":{\"HP\":60,\"Attack\":60,\"Defense\":40,\"Sp. Attack\":65,\"Sp. Defense\":45,\"Speed\":35}},\"Shiny\":false,\"IVs\":{\"hp\":27,\"attack\":22,\"defense\":1,\"speed\":5,\"spatk\":8,\"spdef\":6},\"OriginalOwner\":\"0418b84ba62e0447949ca6837b697842aba1bca946968b81c4b77abe7adfa0b8b4e5058d943f697963b1027c71ebe8feb50c309cee70e1c3692c0ce9ee458dcdae\",\"Gender\":\"male\"}","{\"id\":\"HDAXtYRweMDa7Lg3wk1l5\",\"Pokemon\":{\"id\":538,\"name\":{\"english\":\"Throh\",\"japanese\":\"ナゲキ\",\"chinese\":\"投摔鬼\"},\"type\":[\"Fighting\"],\"base\":{\"HP\":120,\"Attack\":100,\"Defense\":85,\"Sp. Attack\":30,\"Sp. Defense\":85,\"Speed\":45}},\"Shiny\":false,\"IVs\":{\"hp\":10,\"attack\":20,\"defense\":27,\"speed\":3,\"spatk\":7,\"spdef\":6},\"OriginalOwner\":\"0418b84ba62e0447949ca6837b697842aba1bca946968b81c4b77abe7adfa0b8b4e5058d943f697963b1027c71ebe8feb50c309cee70e1c3692c0ce9ee458dcdae\",\"Gender\":\"male\"}"],"timeStamp":1548715710409}],"nonce":35,"hash":"00162e7f615899b235104684b7ac66903f3c7273f6b1a00655a67bc9f91b057a"},{"id":3,"previousHash":"00162e7f615899b235104684b7ac66903f3c7273f6b1a00655a67bc9f91b057a","timestamp":1548715716698,"transactions":[{"fromAddr":null,"toAddr":"0418b84ba62e0447949ca6837b697842aba1bca946968b81c4b77abe7adfa0b8b4e5058d943f697963b1027c71ebe8feb50c309cee70e1c3692c0ce9ee458dcdae","pokemon":["{\"id\":\"YhA52YUA6uuJTlQBuqBr8\",\"Pokemon\":{\"id\":130,\"name\":{\"english\":\"Gyarados\",\"japanese\":\"ギャラドス\",\"chinese\":\"暴鲤龙\"},\"type\":[\"Water\",\"Flying\"],\"base\":{\"HP\":95,\"Attack\":125,\"Defense\":79,\"Sp. Attack\":60,\"Sp. Defense\":100,\"Speed\":81}},\"Shiny\":false,\"IVs\":{\"hp\":29,\"attack\":25,\"defense\":12,\"speed\":11,\"spatk\":4,\"spdef\":6},\"OriginalOwner\":\"0418b84ba62e0447949ca6837b697842aba1bca946968b81c4b77abe7adfa0b8b4e5058d943f697963b1027c71ebe8feb50c309cee70e1c3692c0ce9ee458dcdae\",\"Gender\":\"male\"}","{\"id\":\"Yi4CVWvuYj3V0WHK2ruKq\",\"Pokemon\":{\"id\":102,\"name\":{\"english\":\"Exeggcute\",\"japanese\":\"タマタマ\",\"chinese\":\"蛋蛋\"},\"type\":[\"Grass\",\"Psychic\"],\"base\":{\"HP\":60,\"Attack\":40,\"Defense\":80,\"Sp. Attack\":60,\"Sp. Defense\":45,\"Speed\":40}},\"Shiny\":false,\"IVs\":{\"hp\":4,\"attack\":1,\"defense\":9,\"speed\":28,\"spatk\":12,\"spdef\":10},\"OriginalOwner\":\"0418b84ba62e0447949ca6837b697842aba1bca946968b81c4b77abe7adfa0b8b4e5058d943f697963b1027c71ebe8feb50c309cee70e1c3692c0ce9ee458dcdae\",\"Gender\":\"male\"}","{\"id\":\"C0FFw7OXjR9hQotJKJCT2\",\"Pokemon\":{\"id\":195,\"name\":{\"english\":\"Quagsire\",\"japanese\":\"ヌオー\",\"chinese\":\"沼王\"},\"type\":[\"Water\",\"Ground\"],\"base\":{\"HP\":95,\"Attack\":85,\"Defense\":85,\"Sp. Attack\":65,\"Sp. Defense\":65,\"Speed\":35}},\"Shiny\":false,\"IVs\":{\"hp\":19,\"attack\":29,\"defense\":1,\"speed\":6,\"spatk\":14,\"spdef\":24},\"OriginalOwner\":\"0418b84ba62e0447949ca6837b697842aba1bca946968b81c4b77abe7adfa0b8b4e5058d943f697963b1027c71ebe8feb50c309cee70e1c3692c0ce9ee458dcdae\",\"Gender\":\"male\"}","{\"id\":\"xBKJW3NRoCO66apRj3HWI\",\"Pokemon\":{\"id\":106,\"name\":{\"english\":\"Hitmonlee\",\"japanese\":\"サワムラー\",\"chinese\":\"飞腿郎\"},\"type\":[\"Fighting\"],\"base\":{\"HP\":50,\"Attack\":120,\"Defense\":53,\"Sp. Attack\":35,\"Sp. Defense\":110,\"Speed\":87}},\"Shiny\":false,\"IVs\":{\"hp\":23,\"attack\":23,\"defense\":17,\"speed\":27,\"spatk\":16,\"spdef\":3},\"OriginalOwner\":\"0418b84ba62e0447949ca6837b697842aba1bca946968b81c4b77abe7adfa0b8b4e5058d943f697963b1027c71ebe8feb50c309cee70e1c3692c0ce9ee458dcdae\",\"Gender\":\"male\"}","{\"id\":\"7ak99D6M0J_bs9hrOosLs\",\"Pokemon\":{\"id\":709,\"name\":{\"english\":\"Trevenant\",\"japanese\":\"オーロット\",\"chinese\":\"朽木妖\"},\"type\":[\"Ghost\",\"Grass\"],\"base\":{\"HP\":85,\"Attack\":110,\"Defense\":76,\"Sp. Attack\":65,\"Sp. Defense\":82,\"Speed\":56}},\"Shiny\":false,\"IVs\":{\"hp\":6,\"attack\":21,\"defense\":21,\"speed\":0,\"spatk\":21,\"spdef\":6},\"OriginalOwner\":\"0418b84ba62e0447949ca6837b697842aba1bca946968b81c4b77abe7adfa0b8b4e5058d943f697963b1027c71ebe8feb50c309cee70e1c3692c0ce9ee458dcdae\",\"Gender\":\"male\"}","{\"id\":\"H8ti_5wy6oCzcy1uLWoAY\",\"Pokemon\":{\"id\":337,\"name\":{\"english\":\"Lunatone\",\"japanese\":\"ルナトーン\",\"chinese\":\"月石\"},\"type\":[\"Rock\",\"Psychic\"],\"base\":{\"HP\":90,\"Attack\":55,\"Defense\":65,\"Sp. Attack\":95,\"Sp. Defense\":85,\"Speed\":70}},\"Shiny\":false,\"IVs\":{\"hp\":27,\"attack\":22,\"defense\":0,\"speed\":16,\"spatk\":27,\"spdef\":7},\"OriginalOwner\":\"0418b84ba62e0447949ca6837b697842aba1bca946968b81c4b77abe7adfa0b8b4e5058d943f697963b1027c71ebe8feb50c309cee70e1c3692c0ce9ee458dcdae\",\"Gender\":\"male\"}"],"timeStamp":1548715716698}],"nonce":639,"hash":"00fff936114343d92b95d0da1a0c745f832f2e42906e4cd63871473f1598cbf1"},{"id":4,"previousHash":"00fff936114343d92b95d0da1a0c745f832f2e42906e4cd63871473f1598cbf1","timestamp":1548715718336,"transactions":[{"fromAddr":null,"toAddr":"0418b84ba62e0447949ca6837b697842aba1bca946968b81c4b77abe7adfa0b8b4e5058d943f697963b1027c71ebe8feb50c309cee70e1c3692c0ce9ee458dcdae","pokemon":["{\"id\":\"2TodCbQget3qs5nIGgOWg\",\"Pokemon\":{\"id\":189,\"name\":{\"english\":\"Jumpluff\",\"japanese\":\"ワタッコ\",\"chinese\":\"毽子棉\"},\"type\":[\"Grass\",\"Flying\"],\"base\":{\"HP\":75,\"Attack\":55,\"Defense\":70,\"Sp. Attack\":55,\"Sp. Defense\":95,\"Speed\":110}},\"Shiny\":false,\"IVs\":{\"hp\":12,\"attack\":22,\"defense\":2,\"speed\":4,\"spatk\":5,\"spdef\":17},\"OriginalOwner\":\"0418b84ba62e0447949ca6837b697842aba1bca946968b81c4b77abe7adfa0b8b4e5058d943f697963b1027c71ebe8feb50c309cee70e1c3692c0ce9ee458dcdae\",\"Gender\":\"male\"}","{\"id\":\"8OEsNWZd-FpPqawGmLLjV\",\"Pokemon\":{\"id\":33,\"name\":{\"english\":\"Nidorino\",\"japanese\":\"ニドリーノ\",\"chinese\":\"尼多力诺\"},\"type\":[\"Poison\"],\"base\":{\"HP\":61,\"Attack\":72,\"Defense\":57,\"Sp. Attack\":55,\"Sp. Defense\":55,\"Speed\":65}},\"Shiny\":false,\"IVs\":{\"hp\":16,\"attack\":6,\"defense\":13,\"speed\":26,\"spatk\":1,\"spdef\":22},\"OriginalOwner\":\"0418b84ba62e0447949ca6837b697842aba1bca946968b81c4b77abe7adfa0b8b4e5058d943f697963b1027c71ebe8feb50c309cee70e1c3692c0ce9ee458dcdae\",\"Gender\":\"male\"}","{\"id\":\"KZHU9vmfTRBvyt5x02u0J\",\"Pokemon\":{\"id\":41,\"name\":{\"english\":\"Zubat\",\"japanese\":\"ズバット\",\"chinese\":\"超音蝠\"},\"type\":[\"Poison\",\"Flying\"],\"base\":{\"HP\":40,\"Attack\":45,\"Defense\":35,\"Sp. Attack\":30,\"Sp. Defense\":40,\"Speed\":55}},\"Shiny\":false,\"IVs\":{\"hp\":1,\"attack\":4,\"defense\":1,\"speed\":5,\"spatk\":0,\"spdef\":9},\"OriginalOwner\":\"0418b84ba62e0447949ca6837b697842aba1bca946968b81c4b77abe7adfa0b8b4e5058d943f697963b1027c71ebe8feb50c309cee70e1c3692c0ce9ee458dcdae\",\"Gender\":\"male\"}","{\"id\":\"AkxvTiKqeLHPTap0OndKq\",\"Pokemon\":{\"id\":67,\"name\":{\"english\":\"Machoke\",\"japanese\":\"ゴーリキー\",\"chinese\":\"豪力\"},\"type\":[\"Fighting\"],\"base\":{\"HP\":80,\"Attack\":100,\"Defense\":70,\"Sp. Attack\":50,\"Sp. Defense\":60,\"Speed\":45}},\"Shiny\":false,\"IVs\":{\"hp\":9,\"attack\":27,\"defense\":28,\"speed\":19,\"spatk\":25,\"spdef\":7},\"OriginalOwner\":\"0418b84ba62e0447949ca6837b697842aba1bca946968b81c4b77abe7adfa0b8b4e5058d943f697963b1027c71ebe8feb50c309cee70e1c3692c0ce9ee458dcdae\",\"Gender\":\"male\"}","{\"id\":\"HLMMrRstF5eT4W86MOxfH\",\"Pokemon\":{\"id\":714,\"name\":{\"english\":\"Noibat\",\"japanese\":\"オンバット\",\"chinese\":\"嗡蝠\"},\"type\":[\"Flying\",\"Dragon\"],\"base\":{\"HP\":40,\"Attack\":30,\"Defense\":35,\"Sp. Attack\":45,\"Sp. Defense\":40,\"Speed\":55}},\"Shiny\":false,\"IVs\":{\"hp\":17,\"attack\":7,\"defense\":20,\"speed\":14,\"spatk\":2,\"spdef\":23},\"OriginalOwner\":\"0418b84ba62e0447949ca6837b697842aba1bca946968b81c4b77abe7adfa0b8b4e5058d943f697963b1027c71ebe8feb50c309cee70e1c3692c0ce9ee458dcdae\",\"Gender\":\"male\"}","{\"id\":\"CMVl1a6x-zicTVdX_sra7\",\"Pokemon\":{\"id\":520,\"name\":{\"english\":\"Tranquill\",\"japanese\":\"ハトーボー\",\"chinese\":\"咕咕鸽\"},\"type\":[\"Normal\",\"Flying\"],\"base\":{\"HP\":62,\"Attack\":77,\"Defense\":62,\"Sp. Attack\":50,\"Sp. Defense\":42,\"Speed\":65}},\"Shiny\":false,\"IVs\":{\"hp\":15,\"attack\":9,\"defense\":9,\"speed\":29,\"spatk\":29,\"spdef\":12},\"OriginalOwner\":\"0418b84ba62e0447949ca6837b697842aba1bca946968b81c4b77abe7adfa0b8b4e5058d943f697963b1027c71ebe8feb50c309cee70e1c3692c0ce9ee458dcdae\",\"Gender\":\"male\"}"],"timeStamp":1548715718336}],"nonce":9,"hash":"006c76739aa5f9c863343547142e483707e4f6833e8684b09d982e2d72fc7bf1"},{"id":5,"previousHash":"006c76739aa5f9c863343547142e483707e4f6833e8684b09d982e2d72fc7bf1","timestamp":1548715720148,"transactions":[{"fromAddr":null,"toAddr":"0418b84ba62e0447949ca6837b697842aba1bca946968b81c4b77abe7adfa0b8b4e5058d943f697963b1027c71ebe8feb50c309cee70e1c3692c0ce9ee458dcdae","pokemon":["{\"id\":\"4e7c0suCiEZq0RsTleWa2\",\"Pokemon\":{\"id\":99,\"name\":{\"english\":\"Kingler\",\"japanese\":\"キングラー\",\"chinese\":\"巨钳蟹\"},\"type\":[\"Water\"],\"base\":{\"HP\":55,\"Attack\":130,\"Defense\":115,\"Sp. Attack\":50,\"Sp. Defense\":50,\"Speed\":75}},\"Shiny\":false,\"IVs\":{\"hp\":19,\"attack\":19,\"defense\":22,\"speed\":11,\"spatk\":29,\"spdef\":6},\"OriginalOwner\":\"0418b84ba62e0447949ca6837b697842aba1bca946968b81c4b77abe7adfa0b8b4e5058d943f697963b1027c71ebe8feb50c309cee70e1c3692c0ce9ee458dcdae\",\"Gender\":\"male\"}","{\"id\":\"UfLhemM-YmKDWYRqJjJ1d\",\"Pokemon\":{\"id\":101,\"name\":{\"english\":\"Electrode\",\"japanese\":\"マルマイン\",\"chinese\":\"顽皮雷弹\"},\"type\":[\"Electric\"],\"base\":{\"HP\":60,\"Attack\":50,\"Defense\":70,\"Sp. Attack\":80,\"Sp. Defense\":80,\"Speed\":150}},\"Shiny\":false,\"IVs\":{\"hp\":19,\"attack\":0,\"defense\":24,\"speed\":28,\"spatk\":17,\"spdef\":24},\"OriginalOwner\":\"0418b84ba62e0447949ca6837b697842aba1bca946968b81c4b77abe7adfa0b8b4e5058d943f697963b1027c71ebe8feb50c309cee70e1c3692c0ce9ee458dcdae\",\"Gender\":\"male\"}","{\"id\":\"RttrWwTeme_8owj4IPKUE\",\"Pokemon\":{\"id\":316,\"name\":{\"english\":\"Gulpin\",\"japanese\":\"ゴクリン\",\"chinese\":\"溶食兽\"},\"type\":[\"Poison\"],\"base\":{\"HP\":70,\"Attack\":43,\"Defense\":53,\"Sp. Attack\":43,\"Sp. Defense\":53,\"Speed\":40}},\"Shiny\":false,\"IVs\":{\"hp\":27,\"attack\":11,\"defense\":30,\"speed\":28,\"spatk\":14,\"spdef\":0},\"OriginalOwner\":\"0418b84ba62e0447949ca6837b697842aba1bca946968b81c4b77abe7adfa0b8b4e5058d943f697963b1027c71ebe8feb50c309cee70e1c3692c0ce9ee458dcdae\",\"Gender\":\"male\"}","{\"id\":\"paHwamGa2E0rUaxGdyLSN\",\"Pokemon\":{\"id\":58,\"name\":{\"english\":\"Growlithe\",\"japanese\":\"ガーディ\",\"chinese\":\"卡蒂狗\"},\"type\":[\"Fire\"],\"base\":{\"HP\":55,\"Attack\":70,\"Defense\":45,\"Sp. Attack\":70,\"Sp. Defense\":50,\"Speed\":60}},\"Shiny\":false,\"IVs\":{\"hp\":21,\"attack\":12,\"defense\":2,\"speed\":7,\"spatk\":16,\"spdef\":16},\"OriginalOwner\":\"0418b84ba62e0447949ca6837b697842aba1bca946968b81c4b77abe7adfa0b8b4e5058d943f697963b1027c71ebe8feb50c309cee70e1c3692c0ce9ee458dcdae\",\"Gender\":\"male\"}","{\"id\":\"4fBOv-Nnt8Y6kH_Sl4fzO\",\"Pokemon\":{\"id\":688,\"name\":{\"english\":\"Binacle\",\"japanese\":\"カメテテ\",\"chinese\":\"龟脚脚\"},\"type\":[\"Rock\",\"Water\"],\"base\":{\"HP\":42,\"Attack\":52,\"Defense\":67,\"Sp. Attack\":39,\"Sp. Defense\":56,\"Speed\":50}},\"Shiny\":false,\"IVs\":{\"hp\":12,\"attack\":14,\"defense\":18,\"speed\":0,\"spatk\":11,\"spdef\":9},\"OriginalOwner\":\"0418b84ba62e0447949ca6837b697842aba1bca946968b81c4b77abe7adfa0b8b4e5058d943f697963b1027c71ebe8feb50c309cee70e1c3692c0ce9ee458dcdae\",\"Gender\":\"male\"}","{\"id\":\"P4OPiRKsQAGeundkkvPMp\",\"Pokemon\":{\"id\":792,\"name\":{\"english\":\"Lunala\",\"japanese\":\"ルナアーラ\",\"chinese\":\"露奈雅拉\"},\"type\":[\"Psychic\",\"Ghost\"],\"base\":{\"HP\":137,\"Attack\":113,\"Defense\":89,\"Sp. Attack\":137,\"Sp. Defense\":107,\"Speed\":97}},\"Shiny\":false,\"IVs\":{\"hp\":27,\"attack\":19,\"defense\":5,\"speed\":18,\"spatk\":17,\"spdef\":15},\"OriginalOwner\":\"0418b84ba62e0447949ca6837b697842aba1bca946968b81c4b77abe7adfa0b8b4e5058d943f697963b1027c71ebe8feb50c309cee70e1c3692c0ce9ee458dcdae\",\"Gender\":\"male\"}"],"timeStamp":1548715720148}],"nonce":235,"hash":"0043f76eb8caf0bcdd0f6c4958be339f48ecf0049cd005d77d25e6bc8b716d1c"},{"id":6,"previousHash":"0043f76eb8caf0bcdd0f6c4958be339f48ecf0049cd005d77d25e6bc8b716d1c","timestamp":1548715882829,"transactions":[{"fromAddr":null,"toAddr":"0418b84ba62e0447949ca6837b697842aba1bca946968b81c4b77abe7adfa0b8b4e5058d943f697963b1027c71ebe8feb50c309cee70e1c3692c0ce9ee458dcdae","pokemon":["{\"id\":\"TccsOGrZ5I_OdQLMi51-S\",\"Pokemon\":{\"id\":52,\"name\":{\"english\":\"Meowth\",\"japanese\":\"ニャース\",\"chinese\":\"喵喵\"},\"type\":[\"Normal\"],\"base\":{\"HP\":40,\"Attack\":45,\"Defense\":35,\"Sp. Attack\":40,\"Sp. Defense\":40,\"Speed\":90}},\"Shiny\":false,\"IVs\":{\"hp\":22,\"attack\":15,\"defense\":16,\"speed\":4,\"spatk\":1,\"spdef\":23},\"OriginalOwner\":\"0418b84ba62e0447949ca6837b697842aba1bca946968b81c4b77abe7adfa0b8b4e5058d943f697963b1027c71ebe8feb50c309cee70e1c3692c0ce9ee458dcdae\",\"Gender\":\"male\"}","{\"id\":\"YoIWQkFw3wTFcHlC3tp19\",\"Pokemon\":{\"id\":293,\"name\":{\"english\":\"Whismur\",\"japanese\":\"ゴニョニョ\",\"chinese\":\"咕妞妞\"},\"type\":[\"Normal\"],\"base\":{\"HP\":64,\"Attack\":51,\"Defense\":23,\"Sp. Attack\":51,\"Sp. Defense\":23,\"Speed\":28}},\"Shiny\":false,\"IVs\":{\"hp\":12,\"attack\":5,\"defense\":15,\"speed\":18,\"spatk\":14,\"spdef\":25},\"OriginalOwner\":\"0418b84ba62e0447949ca6837b697842aba1bca946968b81c4b77abe7adfa0b8b4e5058d943f697963b1027c71ebe8feb50c309cee70e1c3692c0ce9ee458dcdae\",\"Gender\":\"male\"}","{\"id\":\"JxZQ4lxoRaHIDl1xe7zQd\",\"Pokemon\":{\"id\":340,\"name\":{\"english\":\"Whiscash\",\"japanese\":\"ナマズン\",\"chinese\":\"鲶鱼王\"},\"type\":[\"Water\",\"Ground\"],\"base\":{\"HP\":110,\"Attack\":78,\"Defense\":73,\"Sp. Attack\":76,\"Sp. Defense\":71,\"Speed\":60}},\"Shiny\":false,\"IVs\":{\"hp\":10,\"attack\":15,\"defense\":3,\"speed\":29,\"spatk\":8,\"spdef\":21},\"OriginalOwner\":\"0418b84ba62e0447949ca6837b697842aba1bca946968b81c4b77abe7adfa0b8b4e5058d943f697963b1027c71ebe8feb50c309cee70e1c3692c0ce9ee458dcdae\",\"Gender\":\"male\"}","{\"id\":\"zExmMBCJE8giKHK-77Dbd\",\"Pokemon\":{\"id\":391,\"name\":{\"english\":\"Monferno\",\"japanese\":\"モウカザル\",\"chinese\":\"猛火猴\"},\"type\":[\"Fire\",\"Fighting\"],\"base\":{\"HP\":64,\"Attack\":78,\"Defense\":52,\"Sp. Attack\":78,\"Sp. Defense\":52,\"Speed\":81}},\"Shiny\":false,\"IVs\":{\"hp\":21,\"attack\":22,\"defense\":0,\"speed\":0,\"spatk\":10,\"spdef\":8},\"OriginalOwner\":\"0418b84ba62e0447949ca6837b697842aba1bca946968b81c4b77abe7adfa0b8b4e5058d943f697963b1027c71ebe8feb50c309cee70e1c3692c0ce9ee458dcdae\",\"Gender\":\"male\"}","{\"id\":\"Bgq0jGdQbzntb35hb4KGF\",\"Pokemon\":{\"id\":539,\"name\":{\"english\":\"Sawk\",\"japanese\":\"ダゲキ\",\"chinese\":\"打击鬼\"},\"type\":[\"Fighting\"],\"base\":{\"HP\":75,\"Attack\":125,\"Defense\":75,\"Sp. Attack\":30,\"Sp. Defense\":75,\"Speed\":85}},\"Shiny\":false,\"IVs\":{\"hp\":14,\"attack\":29,\"defense\":2,\"speed\":24,\"spatk\":15,\"spdef\":10},\"OriginalOwner\":\"0418b84ba62e0447949ca6837b697842aba1bca946968b81c4b77abe7adfa0b8b4e5058d943f697963b1027c71ebe8feb50c309cee70e1c3692c0ce9ee458dcdae\",\"Gender\":\"male\"}","{\"id\":\"6FymiuWePy03FIAE5HfB2\",\"Pokemon\":{\"id\":151,\"name\":{\"english\":\"Mew\",\"japanese\":\"ミュウ\",\"chinese\":\"梦幻\"},\"type\":[\"Psychic\"],\"base\":{\"HP\":100,\"Attack\":100,\"Defense\":100,\"Sp. Attack\":100,\"Sp. Defense\":100,\"Speed\":100}},\"Shiny\":false,\"IVs\":{\"hp\":3,\"attack\":2,\"defense\":6,\"speed\":30,\"spatk\":27,\"spdef\":8},\"OriginalOwner\":\"0418b84ba62e0447949ca6837b697842aba1bca946968b81c4b77abe7adfa0b8b4e5058d943f697963b1027c71ebe8feb50c309cee70e1c3692c0ce9ee458dcdae\",\"Gender\":\"male\"}"],"timeStamp":1548715882829}],"nonce":38,"hash":"0085754d896a59a2742437988b8e8a3ac11453d4662727922d13eade213a0083"},{"id":7,"previousHash":"0085754d896a59a2742437988b8e8a3ac11453d4662727922d13eade213a0083","timestamp":1548715922657,"transactions":[{"fromAddr":null,"toAddr":"0418b84ba62e0447949ca6837b697842aba1bca946968b81c4b77abe7adfa0b8b4e5058d943f697963b1027c71ebe8feb50c309cee70e1c3692c0ce9ee458dcdae","pokemon":["{\"id\":\"Jo-XhWVoGEqZGjhnHgZiI\",\"Pokemon\":{\"id\":617,\"name\":{\"english\":\"Accelgor\",\"japanese\":\"アギルダー\",\"chinese\":\"敏捷虫\"},\"type\":[\"Bug\"],\"base\":{\"HP\":80,\"Attack\":70,\"Defense\":40,\"Sp. Attack\":100,\"Sp. Defense\":60,\"Speed\":145}},\"Shiny\":false,\"IVs\":{\"hp\":19,\"attack\":0,\"defense\":29,\"speed\":28,\"spatk\":19,\"spdef\":9},\"OriginalOwner\":\"0418b84ba62e0447949ca6837b697842aba1bca946968b81c4b77abe7adfa0b8b4e5058d943f697963b1027c71ebe8feb50c309cee70e1c3692c0ce9ee458dcdae\",\"Gender\":\"male\"}","{\"id\":\"DJaY895txa-hKW_vpaszh\",\"Pokemon\":{\"id\":295,\"name\":{\"english\":\"Exploud\",\"japanese\":\"バクオング\",\"chinese\":\"爆音怪\"},\"type\":[\"Normal\"],\"base\":{\"HP\":104,\"Attack\":91,\"Defense\":63,\"Sp. Attack\":91,\"Sp. Defense\":73,\"Speed\":68}},\"Shiny\":false,\"IVs\":{\"hp\":16,\"attack\":27,\"defense\":24,\"speed\":18,\"spatk\":14,\"spdef\":7},\"OriginalOwner\":\"0418b84ba62e0447949ca6837b697842aba1bca946968b81c4b77abe7adfa0b8b4e5058d943f697963b1027c71ebe8feb50c309cee70e1c3692c0ce9ee458dcdae\",\"Gender\":\"male\"}","{\"id\":\"5QK1DBEO2buYyQmHz6vo0\",\"Pokemon\":{\"id\":160,\"name\":{\"english\":\"Feraligatr\",\"japanese\":\"オーダイル\",\"chinese\":\"大力鳄\"},\"type\":[\"Water\"],\"base\":{\"HP\":85,\"Attack\":105,\"Defense\":100,\"Sp. Attack\":79,\"Sp. Defense\":83,\"Speed\":78}},\"Shiny\":false,\"IVs\":{\"hp\":11,\"attack\":14,\"defense\":28,\"speed\":1,\"spatk\":17,\"spdef\":4},\"OriginalOwner\":\"0418b84ba62e0447949ca6837b697842aba1bca946968b81c4b77abe7adfa0b8b4e5058d943f697963b1027c71ebe8feb50c309cee70e1c3692c0ce9ee458dcdae\",\"Gender\":\"male\"}","{\"id\":\"76OPMIU_DGEx08Vp9_wUK\",\"Pokemon\":{\"id\":26,\"name\":{\"english\":\"Raichu\",\"japanese\":\"ライチュウ\",\"chinese\":\"雷丘\"},\"type\":[\"Electric\"],\"base\":{\"HP\":60,\"Attack\":90,\"Defense\":55,\"Sp. Attack\":90,\"Sp. Defense\":80,\"Speed\":110}},\"Shiny\":false,\"IVs\":{\"hp\":30,\"attack\":27,\"defense\":27,\"speed\":22,\"spatk\":0,\"spdef\":28},\"OriginalOwner\":\"0418b84ba62e0447949ca6837b697842aba1bca946968b81c4b77abe7adfa0b8b4e5058d943f697963b1027c71ebe8feb50c309cee70e1c3692c0ce9ee458dcdae\",\"Gender\":\"male\"}","{\"id\":\"GmdfuTJrIS4fT8oKr4iWF\",\"Pokemon\":{\"id\":703,\"name\":{\"english\":\"Carbink\",\"japanese\":\"メレシー\",\"chinese\":\"小碎钻\"},\"type\":[\"Rock\",\"Fairy\"],\"base\":{\"HP\":50,\"Attack\":50,\"Defense\":150,\"Sp. Attack\":50,\"Sp. Defense\":150,\"Speed\":50}},\"Shiny\":false,\"IVs\":{\"hp\":11,\"attack\":25,\"defense\":12,\"speed\":20,\"spatk\":20,\"spdef\":9},\"OriginalOwner\":\"0418b84ba62e0447949ca6837b697842aba1bca946968b81c4b77abe7adfa0b8b4e5058d943f697963b1027c71ebe8feb50c309cee70e1c3692c0ce9ee458dcdae\",\"Gender\":\"male\"}","{\"id\":\"nvGddc9QmqGmhlxSy-6NP\",\"Pokemon\":{\"id\":220,\"name\":{\"english\":\"Swinub\",\"japanese\":\"ウリムー\",\"chinese\":\"小山猪\"},\"type\":[\"Ice\",\"Ground\"],\"base\":{\"HP\":50,\"Attack\":50,\"Defense\":40,\"Sp. Attack\":30,\"Sp. Defense\":30,\"Speed\":50}},\"Shiny\":false,\"IVs\":{\"hp\":25,\"attack\":23,\"defense\":15,\"speed\":1,\"spatk\":6,\"spdef\":17},\"OriginalOwner\":\"0418b84ba62e0447949ca6837b697842aba1bca946968b81c4b77abe7adfa0b8b4e5058d943f697963b1027c71ebe8feb50c309cee70e1c3692c0ce9ee458dcdae\",\"Gender\":\"male\"}"],"timeStamp":1548715922657}],"nonce":309,"hash":"00e929518510d897e1a79a30d9eb2bf95f73d09c87ae8a1b5c45515ddce64d08"},{"id":8,"previousHash":"00e929518510d897e1a79a30d9eb2bf95f73d09c87ae8a1b5c45515ddce64d08","timestamp":1548778975064,"transactions":[{"fromAddr":null,"toAddr":"0418b84ba62e0447949ca6837b697842aba1bca946968b81c4b77abe7adfa0b8b4e5058d943f697963b1027c71ebe8feb50c309cee70e1c3692c0ce9ee458dcdae","pokemon":["{\"id\":\"kLbpeL-XvsKnK2hNpRgX4\",\"Pokemon\":{\"id\":637,\"name\":{\"english\":\"Volcarona\",\"japanese\":\"ウルガモス\",\"chinese\":\"火神蛾\"},\"type\":[\"Bug\",\"Fire\"],\"base\":{\"HP\":85,\"Attack\":60,\"Defense\":65,\"Sp. Attack\":135,\"Sp. Defense\":105,\"Speed\":100}},\"Shiny\":false,\"IVs\":{\"hp\":7,\"attack\":27,\"defense\":3,\"speed\":1,\"spatk\":9,\"spdef\":6},\"OriginalOwner\":\"0418b84ba62e0447949ca6837b697842aba1bca946968b81c4b77abe7adfa0b8b4e5058d943f697963b1027c71ebe8feb50c309cee70e1c3692c0ce9ee458dcdae\",\"Gender\":\"male\"}","{\"id\":\"ysVSjXhBW8K_RzA8bCmn2\",\"Pokemon\":{\"id\":283,\"name\":{\"english\":\"Surskit\",\"japanese\":\"アメタマ\",\"chinese\":\"溜溜糖球\"},\"type\":[\"Bug\",\"Water\"],\"base\":{\"HP\":40,\"Attack\":30,\"Defense\":32,\"Sp. Attack\":50,\"Sp. Defense\":52,\"Speed\":65}},\"Shiny\":false,\"IVs\":{\"hp\":16,\"attack\":6,\"defense\":30,\"speed\":12,\"spatk\":25,\"spdef\":5},\"OriginalOwner\":\"0418b84ba62e0447949ca6837b697842aba1bca946968b81c4b77abe7adfa0b8b4e5058d943f697963b1027c71ebe8feb50c309cee70e1c3692c0ce9ee458dcdae\",\"Gender\":\"male\"}","{\"id\":\"3HaIWlMJLubqmN6ymhJ1e\",\"Pokemon\":{\"id\":510,\"name\":{\"english\":\"Liepard\",\"japanese\":\"レパルダス\",\"chinese\":\"酷豹\"},\"type\":[\"Dark\"],\"base\":{\"HP\":64,\"Attack\":88,\"Defense\":50,\"Sp. Attack\":88,\"Sp. Defense\":50,\"Speed\":106}},\"Shiny\":false,\"IVs\":{\"hp\":25,\"attack\":15,\"defense\":4,\"speed\":22,\"spatk\":2,\"spdef\":4},\"OriginalOwner\":\"0418b84ba62e0447949ca6837b697842aba1bca946968b81c4b77abe7adfa0b8b4e5058d943f697963b1027c71ebe8feb50c309cee70e1c3692c0ce9ee458dcdae\",\"Gender\":\"male\"}","{\"id\":\"p2wqh433xnReOv2HsaqrE\",\"Pokemon\":{\"id\":750,\"name\":{\"english\":\"Mudsdale\",\"japanese\":\"バンバドロ\",\"chinese\":\"重泥挽马\"},\"type\":[\"Ground\"],\"base\":{\"HP\":100,\"Attack\":125,\"Defense\":100,\"Sp. Attack\":55,\"Sp. Defense\":85,\"Speed\":35}},\"Shiny\":false,\"IVs\":{\"hp\":25,\"attack\":30,\"defense\":0,\"speed\":13,\"spatk\":23,\"spdef\":1},\"OriginalOwner\":\"0418b84ba62e0447949ca6837b697842aba1bca946968b81c4b77abe7adfa0b8b4e5058d943f697963b1027c71ebe8feb50c309cee70e1c3692c0ce9ee458dcdae\",\"Gender\":\"male\"}","{\"id\":\"8-5ADlXC8ZDlttJbINMi7\",\"Pokemon\":{\"id\":361,\"name\":{\"english\":\"Snorunt\",\"japanese\":\"ユキワラシ\",\"chinese\":\"雪童子\"},\"type\":[\"Ice\"],\"base\":{\"HP\":50,\"Attack\":50,\"Defense\":50,\"Sp. Attack\":50,\"Sp. Defense\":50,\"Speed\":50}},\"Shiny\":false,\"IVs\":{\"hp\":16,\"attack\":3,\"defense\":24,\"speed\":18,\"spatk\":3,\"spdef\":20},\"OriginalOwner\":\"0418b84ba62e0447949ca6837b697842aba1bca946968b81c4b77abe7adfa0b8b4e5058d943f697963b1027c71ebe8feb50c309cee70e1c3692c0ce9ee458dcdae\",\"Gender\":\"male\"}","{\"id\":\"FgauZNQG2adiNiqcZzEPb\",\"Pokemon\":{\"id\":133,\"name\":{\"english\":\"Eevee\",\"japanese\":\"イーブイ\",\"chinese\":\"伊布\"},\"type\":[\"Normal\"],\"base\":{\"HP\":55,\"Attack\":55,\"Defense\":50,\"Sp. Attack\":45,\"Sp. Defense\":65,\"Speed\":55}},\"Shiny\":false,\"IVs\":{\"hp\":19,\"attack\":29,\"defense\":26,\"speed\":30,\"spatk\":21,\"spdef\":19},\"OriginalOwner\":\"0418b84ba62e0447949ca6837b697842aba1bca946968b81c4b77abe7adfa0b8b4e5058d943f697963b1027c71ebe8feb50c309cee70e1c3692c0ce9ee458dcdae\",\"Gender\":\"male\"}"],"timeStamp":1548778975064}],"nonce":29,"hash":"00367f5f2235982bb0410d3fdcf7bc48eb9997f7628bed2581ad6ecdc3d33ee5"},{"id":9,"previousHash":"00367f5f2235982bb0410d3fdcf7bc48eb9997f7628bed2581ad6ecdc3d33ee5","timestamp":1548779077368,"transactions":[{"fromAddr":null,"toAddr":"0418b84ba62e0447949ca6837b697842aba1bca946968b81c4b77abe7adfa0b8b4e5058d943f697963b1027c71ebe8feb50c309cee70e1c3692c0ce9ee458dcdae","pokemon":["{\"id\":\"t7JvJto17MWvooZv2GrOy\",\"Pokemon\":{\"id\":147,\"name\":{\"english\":\"Dratini\",\"japanese\":\"ミニリュウ\",\"chinese\":\"迷你龙\"},\"type\":[\"Dragon\"],\"base\":{\"HP\":41,\"Attack\":64,\"Defense\":45,\"Sp. Attack\":50,\"Sp. Defense\":50,\"Speed\":50}},\"Shiny\":false,\"IVs\":{\"hp\":30,\"attack\":12,\"defense\":12,\"speed\":18,\"spatk\":22,\"spdef\":20},\"OriginalOwner\":\"0418b84ba62e0447949ca6837b697842aba1bca946968b81c4b77abe7adfa0b8b4e5058d943f697963b1027c71ebe8feb50c309cee70e1c3692c0ce9ee458dcdae\",\"Gender\":\"male\"}","{\"id\":\"3a4TjWJT0KuNUfHJbXyhI\",\"Pokemon\":{\"id\":300,\"name\":{\"english\":\"Skitty\",\"japanese\":\"エネコ\",\"chinese\":\"向尾喵\"},\"type\":[\"Normal\"],\"base\":{\"HP\":50,\"Attack\":45,\"Defense\":45,\"Sp. Attack\":35,\"Sp. Defense\":35,\"Speed\":50}},\"Shiny\":false,\"IVs\":{\"hp\":4,\"attack\":10,\"defense\":3,\"speed\":5,\"spatk\":0,\"spdef\":13},\"OriginalOwner\":\"0418b84ba62e0447949ca6837b697842aba1bca946968b81c4b77abe7adfa0b8b4e5058d943f697963b1027c71ebe8feb50c309cee70e1c3692c0ce9ee458dcdae\",\"Gender\":\"male\"}","{\"id\":\"0Md144SEVNC8TvGfUwXNg\",\"Pokemon\":{\"id\":397,\"name\":{\"english\":\"Staravia\",\"japanese\":\"ムクバード\",\"chinese\":\"姆克鸟\"},\"type\":[\"Normal\",\"Flying\"],\"base\":{\"HP\":55,\"Attack\":75,\"Defense\":50,\"Sp. Attack\":40,\"Sp. Defense\":40,\"Speed\":80}},\"Shiny\":false,\"IVs\":{\"hp\":3,\"attack\":25,\"defense\":11,\"speed\":13,\"spatk\":9,\"spdef\":20},\"OriginalOwner\":\"0418b84ba62e0447949ca6837b697842aba1bca946968b81c4b77abe7adfa0b8b4e5058d943f697963b1027c71ebe8feb50c309cee70e1c3692c0ce9ee458dcdae\",\"Gender\":\"male\"}","{\"id\":\"WIT_gkyNueX7YpFscWRgz\",\"Pokemon\":{\"id\":29,\"name\":{\"english\":\"Nidoran♀\",\"japanese\":\"ニドラン♀\",\"chinese\":\"尼多兰\"},\"type\":[\"Poison\"],\"base\":{\"HP\":55,\"Attack\":47,\"Defense\":52,\"Sp. Attack\":40,\"Sp. Defense\":40,\"Speed\":41}},\"Shiny\":false,\"IVs\":{\"hp\":14,\"attack\":19,\"defense\":22,\"speed\":4,\"spatk\":15,\"spdef\":11},\"OriginalOwner\":\"0418b84ba62e0447949ca6837b697842aba1bca946968b81c4b77abe7adfa0b8b4e5058d943f697963b1027c71ebe8feb50c309cee70e1c3692c0ce9ee458dcdae\",\"Gender\":\"male\"}","{\"id\":\"-UvU35Q5yeY8FGvsY8zom\",\"Pokemon\":{\"id\":719,\"name\":{\"english\":\"Diancie\",\"japanese\":\"ディアンシー\",\"chinese\":\"蒂安希\"},\"type\":[\"Rock\",\"Fairy\"],\"base\":{\"HP\":50,\"Attack\":100,\"Defense\":150,\"Sp. Attack\":100,\"Sp. Defense\":150,\"Speed\":50}},\"Shiny\":false,\"IVs\":{\"hp\":9,\"attack\":7,\"defense\":12,\"speed\":10,\"spatk\":5,\"spdef\":3},\"OriginalOwner\":\"0418b84ba62e0447949ca6837b697842aba1bca946968b81c4b77abe7adfa0b8b4e5058d943f697963b1027c71ebe8feb50c309cee70e1c3692c0ce9ee458dcdae\",\"Gender\":\"male\"}","{\"id\":\"2WPCo_z_8lWfwg0J_45zN\",\"Pokemon\":{\"id\":370,\"name\":{\"english\":\"Luvdisc\",\"japanese\":\"ラブカス\",\"chinese\":\"爱心鱼\"},\"type\":[\"Water\"],\"base\":{\"HP\":43,\"Attack\":30,\"Defense\":55,\"Sp. Attack\":40,\"Sp. Defense\":65,\"Speed\":97}},\"Shiny\":false,\"IVs\":{\"hp\":18,\"attack\":21,\"defense\":7,\"speed\":0,\"spatk\":10,\"spdef\":0},\"OriginalOwner\":\"0418b84ba62e0447949ca6837b697842aba1bca946968b81c4b77abe7adfa0b8b4e5058d943f697963b1027c71ebe8feb50c309cee70e1c3692c0ce9ee458dcdae\",\"Gender\":\"male\"}"],"timeStamp":1548779077368}],"nonce":135,"hash":"005181693a318ab5e6c2c22719d0aafcef0ea4d3f4309f7ce41d0d1c30fdb6a1"},{"id":10,"previousHash":"005181693a318ab5e6c2c22719d0aafcef0ea4d3f4309f7ce41d0d1c30fdb6a1","timestamp":1548779101503,"transactions":[{"fromAddr":null,"toAddr":"0418b84ba62e0447949ca6837b697842aba1bca946968b81c4b77abe7adfa0b8b4e5058d943f697963b1027c71ebe8feb50c309cee70e1c3692c0ce9ee458dcdae","pokemon":["{\"id\":\"HIoyXL8VsOyxWW7ST9Nv3\",\"Pokemon\":{\"id\":558,\"name\":{\"english\":\"Crustle\",\"japanese\":\"イワパレス\",\"chinese\":\"岩殿居蟹\"},\"type\":[\"Bug\",\"Rock\"],\"base\":{\"HP\":70,\"Attack\":105,\"Defense\":125,\"Sp. Attack\":65,\"Sp. Defense\":75,\"Speed\":45}},\"Shiny\":false,\"IVs\":{\"hp\":4,\"attack\":16,\"defense\":14,\"speed\":7,\"spatk\":23,\"spdef\":17},\"OriginalOwner\":\"0418b84ba62e0447949ca6837b697842aba1bca946968b81c4b77abe7adfa0b8b4e5058d943f697963b1027c71ebe8feb50c309cee70e1c3692c0ce9ee458dcdae\",\"Gender\":\"male\"}","{\"id\":\"F49x_anAQRepp0JmB9CoY\",\"Pokemon\":{\"id\":424,\"name\":{\"english\":\"Ambipom\",\"japanese\":\"エテボース\",\"chinese\":\"双尾怪手\"},\"type\":[\"Normal\"],\"base\":{\"HP\":75,\"Attack\":100,\"Defense\":66,\"Sp. Attack\":60,\"Sp. Defense\":66,\"Speed\":115}},\"Shiny\":false,\"IVs\":{\"hp\":7,\"attack\":0,\"defense\":30,\"speed\":3,\"spatk\":26,\"spdef\":15},\"OriginalOwner\":\"0418b84ba62e0447949ca6837b697842aba1bca946968b81c4b77abe7adfa0b8b4e5058d943f697963b1027c71ebe8feb50c309cee70e1c3692c0ce9ee458dcdae\",\"Gender\":\"male\"}","{\"id\":\"Cn1YGp20PatMy8twD25Ev\",\"Pokemon\":{\"id\":574,\"name\":{\"english\":\"Gothita\",\"japanese\":\"ゴチム\",\"chinese\":\"哥德宝宝\"},\"type\":[\"Psychic\"],\"base\":{\"HP\":45,\"Attack\":30,\"Defense\":50,\"Sp. Attack\":55,\"Sp. Defense\":65,\"Speed\":45}},\"Shiny\":false,\"IVs\":{\"hp\":28,\"attack\":24,\"defense\":19,\"speed\":15,\"spatk\":6,\"spdef\":18},\"OriginalOwner\":\"0418b84ba62e0447949ca6837b697842aba1bca946968b81c4b77abe7adfa0b8b4e5058d943f697963b1027c71ebe8feb50c309cee70e1c3692c0ce9ee458dcdae\",\"Gender\":\"male\"}","{\"id\":\"XB_8SzlGzxsb6VzCOsscC\",\"Pokemon\":{\"id\":769,\"name\":{\"english\":\"Sandygast\",\"japanese\":\"スナバァ\",\"chinese\":\"沙丘娃\"},\"type\":[\"Ghost\",\"Ground\"],\"base\":{\"HP\":55,\"Attack\":55,\"Defense\":80,\"Sp. Attack\":70,\"Sp. Defense\":45,\"Speed\":15}},\"Shiny\":false,\"IVs\":{\"hp\":6,\"attack\":23,\"defense\":14,\"speed\":24,\"spatk\":15,\"spdef\":25},\"OriginalOwner\":\"0418b84ba62e0447949ca6837b697842aba1bca946968b81c4b77abe7adfa0b8b4e5058d943f697963b1027c71ebe8feb50c309cee70e1c3692c0ce9ee458dcdae\",\"Gender\":\"male\"}","{\"id\":\"K3rfQ1SPx8Uyyavf-GhVg\",\"Pokemon\":{\"id\":21,\"name\":{\"english\":\"Spearow\",\"japanese\":\"オニスズメ\",\"chinese\":\"烈雀\"},\"type\":[\"Normal\",\"Flying\"],\"base\":{\"HP\":40,\"Attack\":60,\"Defense\":30,\"Sp. Attack\":31,\"Sp. Defense\":31,\"Speed\":70}},\"Shiny\":false,\"IVs\":{\"hp\":22,\"attack\":26,\"defense\":7,\"speed\":22,\"spatk\":12,\"spdef\":7},\"OriginalOwner\":\"0418b84ba62e0447949ca6837b697842aba1bca946968b81c4b77abe7adfa0b8b4e5058d943f697963b1027c71ebe8feb50c309cee70e1c3692c0ce9ee458dcdae\",\"Gender\":\"male\"}","{\"id\":\"YzScmvjnUn9RVNI2fEdAQ\",\"Pokemon\":{\"id\":182,\"name\":{\"english\":\"Bellossom\",\"japanese\":\"キレイハナ\",\"chinese\":\"美丽花\"},\"type\":[\"Grass\"],\"base\":{\"HP\":75,\"Attack\":80,\"Defense\":95,\"Sp. Attack\":90,\"Sp. Defense\":100,\"Speed\":50}},\"Shiny\":false,\"IVs\":{\"hp\":20,\"attack\":8,\"defense\":3,\"speed\":7,\"spatk\":29,\"spdef\":18},\"OriginalOwner\":\"0418b84ba62e0447949ca6837b697842aba1bca946968b81c4b77abe7adfa0b8b4e5058d943f697963b1027c71ebe8feb50c309cee70e1c3692c0ce9ee458dcdae\",\"Gender\":\"male\"}"],"timeStamp":1548779101503}],"nonce":145,"hash":"004c74d7709dcea9a73b5e6c3e44b06054143d4c5819dd7868424d3d786753cf"},{"id":11,"previousHash":"004c74d7709dcea9a73b5e6c3e44b06054143d4c5819dd7868424d3d786753cf","timestamp":1548780585278,"transactions":[{"fromAddr":null,"toAddr":"0418b84ba62e0447949ca6837b697842aba1bca946968b81c4b77abe7adfa0b8b4e5058d943f697963b1027c71ebe8feb50c309cee70e1c3692c0ce9ee458dcdae","pokemon":["{\"id\":\"gPzkcqyYyd6MV-YKs5WQb\",\"Pokemon\":{\"id\":261,\"name\":{\"english\":\"Poochyena\",\"japanese\":\"ポチエナ\",\"chinese\":\"土狼犬\"},\"type\":[\"Dark\"],\"base\":{\"HP\":35,\"Attack\":55,\"Defense\":35,\"Sp. Attack\":30,\"Sp. Defense\":30,\"Speed\":35}},\"Shiny\":false,\"IVs\":{\"hp\":15,\"attack\":22,\"defense\":8,\"speed\":18,\"spatk\":25,\"spdef\":29},\"OriginalOwner\":\"0418b84ba62e0447949ca6837b697842aba1bca946968b81c4b77abe7adfa0b8b4e5058d943f697963b1027c71ebe8feb50c309cee70e1c3692c0ce9ee458dcdae\",\"Gender\":\"male\"}","{\"id\":\"L9zjwxNFKUStW0lDvoZCY\",\"Pokemon\":{\"id\":98,\"name\":{\"english\":\"Krabby\",\"japanese\":\"クラブ\",\"chinese\":\"大钳蟹\"},\"type\":[\"Water\"],\"base\":{\"HP\":30,\"Attack\":105,\"Defense\":90,\"Sp. Attack\":25,\"Sp. Defense\":25,\"Speed\":50}},\"Shiny\":false,\"IVs\":{\"hp\":18,\"attack\":21,\"defense\":11,\"speed\":10,\"spatk\":17,\"spdef\":27},\"OriginalOwner\":\"0418b84ba62e0447949ca6837b697842aba1bca946968b81c4b77abe7adfa0b8b4e5058d943f697963b1027c71ebe8feb50c309cee70e1c3692c0ce9ee458dcdae\",\"Gender\":\"male\"}","{\"id\":\"T1DhW5xg3-YH5NcqB8NJV\",\"Pokemon\":{\"id\":753,\"name\":{\"english\":\"Fomantis\",\"japanese\":\"カリキリ\",\"chinese\":\"伪螳草\"},\"type\":[\"Grass\"],\"base\":{\"HP\":40,\"Attack\":55,\"Defense\":35,\"Sp. Attack\":50,\"Sp. Defense\":35,\"Speed\":35}},\"Shiny\":false,\"IVs\":{\"hp\":26,\"attack\":25,\"defense\":14,\"speed\":4,\"spatk\":24,\"spdef\":5},\"OriginalOwner\":\"0418b84ba62e0447949ca6837b697842aba1bca946968b81c4b77abe7adfa0b8b4e5058d943f697963b1027c71ebe8feb50c309cee70e1c3692c0ce9ee458dcdae\",\"Gender\":\"male\"}","{\"id\":\"hBvoOkytdrbwIOHT7ffrH\",\"Pokemon\":{\"id\":658,\"name\":{\"english\":\"Greninja\",\"japanese\":\"ゲッコウガ\",\"chinese\":\"甲贺忍蛙\"},\"type\":[\"Water\",\"Dark\"],\"base\":{\"HP\":72,\"Attack\":95,\"Defense\":67,\"Sp. Attack\":103,\"Sp. Defense\":71,\"Speed\":122}},\"Shiny\":false,\"IVs\":{\"hp\":22,\"attack\":9,\"defense\":10,\"speed\":22,\"spatk\":23,\"spdef\":11},\"OriginalOwner\":\"0418b84ba62e0447949ca6837b697842aba1bca946968b81c4b77abe7adfa0b8b4e5058d943f697963b1027c71ebe8feb50c309cee70e1c3692c0ce9ee458dcdae\",\"Gender\":\"male\"}","{\"id\":\"Zvk8kxTcBiztfhi14Zkt2\",\"Pokemon\":{\"id\":457,\"name\":{\"english\":\"Lumineon\",\"japanese\":\"ネオラント\",\"chinese\":\"霓虹鱼\"},\"type\":[\"Water\"],\"base\":{\"HP\":69,\"Attack\":69,\"Defense\":76,\"Sp. Attack\":69,\"Sp. Defense\":86,\"Speed\":91}},\"Shiny\":false,\"IVs\":{\"hp\":26,\"attack\":11,\"defense\":11,\"speed\":19,\"spatk\":29,\"spdef\":25},\"OriginalOwner\":\"0418b84ba62e0447949ca6837b697842aba1bca946968b81c4b77abe7adfa0b8b4e5058d943f697963b1027c71ebe8feb50c309cee70e1c3692c0ce9ee458dcdae\",\"Gender\":\"male\"}","{\"id\":\"nGhYXORxo77eE9o4wdpV6\",\"Pokemon\":{\"id\":710,\"name\":{\"english\":\"Pumpkaboo\",\"japanese\":\"バケッチャ\",\"chinese\":\"南瓜精\"},\"type\":[\"Ghost\",\"Grass\"],\"base\":{\"HP\":59,\"Attack\":66,\"Defense\":70,\"Sp. Attack\":44,\"Sp. Defense\":55,\"Speed\":41}},\"Shiny\":false,\"IVs\":{\"hp\":12,\"attack\":28,\"defense\":22,\"speed\":8,\"spatk\":9,\"spdef\":17},\"OriginalOwner\":\"0418b84ba62e0447949ca6837b697842aba1bca946968b81c4b77abe7adfa0b8b4e5058d943f697963b1027c71ebe8feb50c309cee70e1c3692c0ce9ee458dcdae\",\"Gender\":\"male\"}"],"timeStamp":1548780585278}],"nonce":56,"hash":"003361675a3ffc73edc612d7ae063f8314dd7f2b56b2107f3802d6f623889f14"},{"id":12,"previousHash":"003361675a3ffc73edc612d7ae063f8314dd7f2b56b2107f3802d6f623889f14","timestamp":1548781209232,"transactions":[{"fromAddr":null,"toAddr":"0418b84ba62e0447949ca6837b697842aba1bca946968b81c4b77abe7adfa0b8b4e5058d943f697963b1027c71ebe8feb50c309cee70e1c3692c0ce9ee458dcdae","pokemon":["{\"id\":\"FOrZxvzWG6jOu55XrEhEA\",\"Pokemon\":{\"id\":748,\"name\":{\"english\":\"Toxapex\",\"japanese\":\"ドヒドイデ\",\"chinese\":\"超坏星\"},\"type\":[\"Poison\",\"Water\"],\"base\":{\"HP\":50,\"Attack\":63,\"Defense\":152,\"Sp. Attack\":53,\"Sp. Defense\":142,\"Speed\":35}},\"Shiny\":false,\"IVs\":{\"hp\":28,\"attack\":30,\"defense\":28,\"speed\":26,\"spatk\":24,\"spdef\":16},\"OriginalOwner\":\"0418b84ba62e0447949ca6837b697842aba1bca946968b81c4b77abe7adfa0b8b4e5058d943f697963b1027c71ebe8feb50c309cee70e1c3692c0ce9ee458dcdae\",\"Gender\":\"male\"}","{\"id\":\"FMOUv63J8WhS8nwJljYG9\",\"Pokemon\":{\"id\":807,\"name\":{\"english\":\"Zeraora\",\"japanese\":\"ゼラオラ\",\"chinese\":\"捷拉奥拉\"},\"type\":[\"Electric\"],\"base\":{\"HP\":88,\"Attack\":112,\"Defense\":75,\"Sp. Attack\":102,\"Sp. Defense\":80,\"Speed\":143}},\"Shiny\":false,\"IVs\":{\"hp\":5,\"attack\":25,\"defense\":17,\"speed\":29,\"spatk\":3,\"spdef\":11},\"OriginalOwner\":\"0418b84ba62e0447949ca6837b697842aba1bca946968b81c4b77abe7adfa0b8b4e5058d943f697963b1027c71ebe8feb50c309cee70e1c3692c0ce9ee458dcdae\",\"Gender\":\"male\"}","{\"id\":\"STmP42XkibjlpMmKuad34\",\"Pokemon\":{\"id\":382,\"name\":{\"english\":\"Kyogre\",\"japanese\":\"カイオーガ\",\"chinese\":\"盖欧卡\"},\"type\":[\"Water\"],\"base\":{\"HP\":100,\"Attack\":100,\"Defense\":90,\"Sp. Attack\":150,\"Sp. Defense\":140,\"Speed\":90}},\"Shiny\":false,\"IVs\":{\"hp\":10,\"attack\":4,\"defense\":8,\"speed\":7,\"spatk\":14,\"spdef\":6},\"OriginalOwner\":\"0418b84ba62e0447949ca6837b697842aba1bca946968b81c4b77abe7adfa0b8b4e5058d943f697963b1027c71ebe8feb50c309cee70e1c3692c0ce9ee458dcdae\",\"Gender\":\"male\"}","{\"id\":\"u_hSUuJTiigXEHSGXq1x2\",\"Pokemon\":{\"id\":316,\"name\":{\"english\":\"Gulpin\",\"japanese\":\"ゴクリン\",\"chinese\":\"溶食兽\"},\"type\":[\"Poison\"],\"base\":{\"HP\":70,\"Attack\":43,\"Defense\":53,\"Sp. Attack\":43,\"Sp. Defense\":53,\"Speed\":40}},\"Shiny\":false,\"IVs\":{\"hp\":25,\"attack\":25,\"defense\":27,\"speed\":0,\"spatk\":6,\"spdef\":0},\"OriginalOwner\":\"0418b84ba62e0447949ca6837b697842aba1bca946968b81c4b77abe7adfa0b8b4e5058d943f697963b1027c71ebe8feb50c309cee70e1c3692c0ce9ee458dcdae\",\"Gender\":\"male\"}","{\"id\":\"7KAubCYZp1srbEIoSlmp5\",\"Pokemon\":{\"id\":334,\"name\":{\"english\":\"Altaria\",\"japanese\":\"チルタリス\",\"chinese\":\"七夕青鸟\"},\"type\":[\"Dragon\",\"Flying\"],\"base\":{\"HP\":75,\"Attack\":70,\"Defense\":90,\"Sp. Attack\":70,\"Sp. Defense\":105,\"Speed\":80}},\"Shiny\":false,\"IVs\":{\"hp\":8,\"attack\":6,\"defense\":1,\"speed\":4,\"spatk\":27,\"spdef\":30},\"OriginalOwner\":\"0418b84ba62e0447949ca6837b697842aba1bca946968b81c4b77abe7adfa0b8b4e5058d943f697963b1027c71ebe8feb50c309cee70e1c3692c0ce9ee458dcdae\",\"Gender\":\"male\"}","{\"id\":\"rEdh9pnXQTd-Vy7BvSMSC\",\"Pokemon\":{\"id\":348,\"name\":{\"english\":\"Armaldo\",\"japanese\":\"アーマルド\",\"chinese\":\"太古盔甲\"},\"type\":[\"Rock\",\"Bug\"],\"base\":{\"HP\":75,\"Attack\":125,\"Defense\":100,\"Sp. Attack\":70,\"Sp. Defense\":80,\"Speed\":45}},\"Shiny\":false,\"IVs\":{\"hp\":23,\"attack\":16,\"defense\":15,\"speed\":11,\"spatk\":0,\"spdef\":7},\"OriginalOwner\":\"0418b84ba62e0447949ca6837b697842aba1bca946968b81c4b77abe7adfa0b8b4e5058d943f697963b1027c71ebe8feb50c309cee70e1c3692c0ce9ee458dcdae\",\"Gender\":\"male\"}"],"timeStamp":1548781209232}],"nonce":584,"hash":"0067ba317b32a9a71dda346adb5b8c38ec4602472e8f6d74f23690ec49b5b54f"}]